{"corrections":[{"data":{"content":[{"key":"central","value":{"content":[{"key":"M","value":{"content":[{"key":0,"value":{"content":[{"content":[0.0,0.02733232278226273,0.015912204032289014,0.013360461710960512,0.009771641281142563,0.009722960645534353,0.011369956891838433,0.015656927930898606,0.03070294642585231],"edges":[20.0,30.0,50.0,70.0,100.0,140.0,200.0,300.0,600.0,1000.0],"flow":"clamp","input":"pt","nodetype":"binning"}],"edges":[0.0,2.5],"flow":"error","input":"abseta","nodetype":"binning"}},{"key":4,"value":{"content":[{"content":[0.0,0.10817207182833576,0.08946881228342005,0.08645010816488322,0.0790578345009868,0.0759265866665357,0.09229450339393301,0.1034325213288073,0.16091562803078574],"edges":[20.0,30.0,50.0,70.0,100.0,140.0,200.0,300.0,600.0,1000.0],"flow":"clamp","input":"pt","nodetype":"binning"}],"edges":[0.0,2.5],"flow":"error","input":"abseta","nodetype":"binning"}},{"key":5,"value":{"content":[{"content":[0.0,0.8178933576612075,0.847642787809837,0.8673318143491104,0.87680312506018,0.8874306272889215,0.8848943708040533,0.874150916018019,0.8550268517633286],"edges":[20.0,30.0,50.0,70.0,100.0,140.0,200.0,300.0,600.0,1000.0],"flow":"clamp","input":"pt","nodetype":"binning"}],"edges":[0.0,2.5],"flow":"error","input":"abseta","nodetype":"binning"}}],"input":"flavor","nodetype":"category"}}],"input":"working_point","nodetype":"category"}}],"input":"systematic","nodetype":"category"},"description":"UParTAK4 efficiency for 2024_Summer24 for b-tagging.","inputs":[{"name":"systematic","type":"string"},{"description":"M","name":"working_point","type":"string"},{"description":"hadron flavor definition: 5=b, 4=c, 0=udsg","name":"flavor","type":"int"},{"name":"abseta","type":"real"},{"name":"pt","type":"real"}],"name":"UParTAK4_eff_values","output":{"name":"weight","type":"real"},"version":1}],"description":"Efficiency for UParTAK4 in 2024_Summer24.","schema_version":2}
